{
  "__inputs": [
    {
      "name": "DS_PROMETHEUS",
      "label": "Prometheus",
      "description": "",
      "type": "datasource",
      "pluginId": "prometheus",
      "pluginName": "Prometheus"
    }
  ],
  "__elements": [],
  "__requires": [
    {
      "type": "grafana",
      "id": "grafana",
      "name": "Grafana",
      "version": "8.5.5"
    },
    {
      "type": "datasource",
      "id": "prometheus",
      "name": "Prometheus",
      "version": "1.0.0"
    },
    {
      "type": "panel",
      "id": "stat",
      "name": "Stat",
      "version": ""
    },
    {
      "type": "panel",
      "id": "table",
      "name": "Table",
      "version": ""
    },
    {
      "type": "panel",
      "id": "timeseries",
      "name": "Time series",
      "version": ""
    }
  ],
  "annotations": {
    "list": [
      {
        "builtIn": 1,
        "datasource": {
          "type": "datasource",
          "uid": "grafana"
        },
        "enable": true,
        "hide": true,
        "iconColor": "rgba(0, 211, 255, 1)",
        "name": "Annotations & Alerts",
        "target": {
          "limit": 100,
          "matchAny": false,
          "tags": [],
          "type": "dashboard"
        },
        "type": "dashboard"
      }
    ]
  },
  "description": "By: TheChrisTech",
  "editable": true,
  "fiscalYearStartMonth": 0,
  "graphTooltip": 1,
  "id": null,
  "iteration": 1710356928554,
  "links": [
    {
      "icon": "external link",
      "tags": [],
      "targetBlank": true,
      "title": "Storj-Exporter Github page",
      "tooltip": "",
      "type": "link",
      "url": "https://github.com/thechristech/Storj-Exporter"
    },
    {
      "icon": "question",
      "tags": [],
      "targetBlank": true,
      "title": "Storj-Exporter forum thread",
      "type": "link",
      "url": "https://forum.storj.io/t/prometheus-storj-exporter/"
    },
    {
      "icon": "bolt",
      "tags": [],
      "targetBlank": true,
      "title": "Support the project ❤️",
      "tooltip": "",
      "type": "link",
      "url": "https://www.buymeacoffee.com/thechristech"
    }
  ],
  "liveNow": false,
  "panels": [
    {
      "collapsed": false,
      "datasource": {
        "uid": "$datasource"
      },
      "gridPos": {
        "h": 1,
        "w": 24,
        "x": 0,
        "y": 0
      },
      "id": 295,
      "panels": [],
      "title": "Combined summary",
      "type": "row"
    },
    {
      "datasource": {
        "type": "prometheus",
        "uid": "$datasource"
      },
      "fieldConfig": {
        "defaults": {
          "mappings": [
            {
              "options": {
                "match": "null",
                "result": {
                  "text": "N/A"
                }
              },
              "type": "special"
            }
          ],
          "min": 0,
          "thresholds": {
            "mode": "absolute",
            "steps": [
              {
                "color": "rgb(180, 214, 180)",
                "value": null
              }
            ]
          },
          "unit": "short"
        },
        "overrides": []
      },
      "gridPos": {
        "h": 4,
        "w": 2,
        "x": 0,
        "y": 1
      },
      "id": 330,
      "links": [],
      "maxDataPoints": 100,
      "options": {
        "colorMode": "background",
        "graphMode": "area",
        "justifyMode": "auto",
        "orientation": "horizontal",
        "reduceOptions": {
          "calcs": [
            "last"
          ],
          "fields": "",
          "values": false
        },
        "text": {},
        "textMode": "value_and_name"
      },
      "pluginVersion": "8.5.5",
      "targets": [
        {
          "datasource": {
            "type": "prometheus",
            "uid": "${DS_PROMETHEUS}"
          },
          "expr": "count(storj_node_info{job=~\"$job.*\",type=\"nodeID\"})",
          "format": "time_series",
          "hide": false,
          "instant": false,
          "interval": "",
          "intervalFactor": 1,
          "legendFormat": "Online",
          "refId": "D"
        }
      ],
      "title": "Nodes online",
      "type": "stat"
    },
    {
      "datasource": {
        "type": "prometheus",
        "uid": "$datasource"
      },
      "fieldConfig": {
        "defaults": {
          "decimals": 3,
          "mappings": [
            {
              "options": {
                "match": "null",
                "result": {
                  "text": "N/A"
                }
              },
              "type": "special"
            }
          ],
          "thresholds": {
            "mode": "absolute",
            "steps": [
              {
                "color": "dark-blue",
                "value": null
              }
            ]
          },
          "unit": "decbytes"
        },
        "overrides": [
          {
            "matcher": {
              "id": "byName",
              "options": "Net out"
            },
            "properties": [
              {
                "id": "color",
                "value": {
                  "fixedColor": "green",
                  "mode": "fixed"
                }
              }
            ]
          }
        ]
      },
      "gridPos": {
        "h": 4,
        "w": 5,
        "x": 2,
        "y": 1
      },
      "id": 328,
      "links": [],
      "maxDataPoints": 100,
      "options": {
        "colorMode": "background",
        "graphMode": "area",
        "justifyMode": "auto",
        "orientation": "vertical",
        "reduceOptions": {
          "calcs": [
            "lastNotNull"
          ],
          "fields": "",
          "values": false
        },
        "text": {},
        "textMode": "value_and_name"
      },
      "pluginVersion": "8.5.5",
      "targets": [
        {
          "datasource": {
            "type": "prometheus",
            "uid": "${DS_PROMETHEUS}"
          },
          "expr": "sum(storj_sat_month_egress{job=~\"$job.*\"})",
          "format": "time_series",
          "hide": false,
          "instant": false,
          "interval": "",
          "intervalFactor": 1,
          "legendFormat": "Net out",
          "refId": "D"
        },
        {
          "datasource": {
            "type": "prometheus",
            "uid": "${DS_PROMETHEUS}"
          },
          "expr": "sum(storj_sat_month_ingress{job=~\"$job.*\"})",
          "format": "time_series",
          "hide": false,
          "instant": false,
          "interval": "",
          "intervalFactor": 1,
          "legendFormat": "Net in",
          "refId": "A"
        }
      ],
      "title": "Net IO total",
      "type": "stat"
    },
    {
      "datasource": {
        "type": "prometheus",
        "uid": "$datasource"
      },
      "fieldConfig": {
        "defaults": {
          "color": {
            "fixedColor": "dark-blue",
            "mode": "fixed"
          },
          "links": [],
          "mappings": [],
          "min": 0,
          "thresholds": {
            "mode": "absolute",
            "steps": [
              {
                "color": "green",
                "value": null
              }
            ]
          },
          "unit": "decbytes"
        },
        "overrides": [
          {
            "matcher": {
              "id": "byName",
              "options": "Disk trash"
            },
            "properties": [
              {
                "id": "color",
                "value": {
                  "fixedColor": "rgb(43, 56, 104)",
                  "mode": "fixed"
                }
              }
            ]
          },
          {
            "matcher": {
              "id": "byName",
              "options": "Disk free"
            },
            "properties": [
              {
                "id": "color",
                "value": {
                  "fixedColor": "blue",
                  "mode": "fixed"
                }
              }
            ]
          },
          {
            "matcher": {
              "id": "byName",
              "options": "Disk total"
            },
            "properties": [
              {
                "id": "color",
                "value": {
                  "fixedColor": "rgb(56, 82, 122)",
                  "mode": "fixed"
                }
              }
            ]
          }
        ]
      },
      "gridPos": {
        "h": 4,
        "w": 9,
        "x": 7,
        "y": 1
      },
      "id": 302,
      "links": [],
      "options": {
        "colorMode": "background",
        "graphMode": "area",
        "justifyMode": "auto",
        "orientation": "auto",
        "reduceOptions": {
          "calcs": [
            "lastNotNull"
          ],
          "fields": "",
          "values": false
        },
        "text": {},
        "textMode": "value_and_name"
      },
      "pluginVersion": "8.5.5",
      "targets": [
        {
          "datasource": {
            "type": "prometheus",
            "uid": "${DS_PROMETHEUS}"
          },
          "expr": "sum(storj_total_diskspace{type=\"available\",job=~\"$job.*\"})",
          "format": "time_series",
          "hide": false,
          "instant": false,
          "interval": "",
          "intervalFactor": 1,
          "legendFormat": "Disk total",
          "refId": "D"
        },
        {
          "datasource": {
            "type": "prometheus",
            "uid": "${DS_PROMETHEUS}"
          },
          "expr": "sum (storj_total_diskspace{type=\"used\",job=~\"$job.*\"})",
          "format": "time_series",
          "hide": false,
          "instant": false,
          "interval": "",
          "intervalFactor": 1,
          "legendFormat": "Disk used",
          "refId": "B"
        },
        {
          "datasource": {
            "type": "prometheus",
            "uid": "${DS_PROMETHEUS}"
          },
          "expr": "sum (storj_total_diskspace{type=\"available\",job=~\"$job.*\"}) - sum (storj_total_diskspace{type=\"used\",job=~\"$job.*\"})",
          "format": "time_series",
          "hide": false,
          "instant": false,
          "interval": "",
          "intervalFactor": 1,
          "legendFormat": "Disk free",
          "refId": "A"
        },
        {
          "datasource": {
            "type": "prometheus",
            "uid": "${DS_PROMETHEUS}"
          },
          "expr": "sum (storj_total_diskspace{type=\"trash\",job=~\"$job.*\"})",
          "format": "time_series",
          "hide": false,
          "instant": false,
          "interval": "",
          "intervalFactor": 1,
          "legendFormat": "Disk trash",
          "refId": "C"
        }
      ],
      "title": "Storage total",
      "type": "stat",
      "valueFontSize": "80%"
    },
    {
      "datasource": {
        "type": "prometheus",
        "uid": "$datasource"
      },
      "fieldConfig": {
        "defaults": {
          "decimals": 2,
          "mappings": [
            {
              "options": {
                "match": "null",
                "result": {
                  "text": "N/A"
                }
              },
              "type": "special"
            }
          ],
          "min": 0,
          "thresholds": {
            "mode": "absolute",
            "steps": [
              {
                "color": "green",
                "value": null
              }
            ]
          },
          "unit": "currencyUSD"
        },
        "overrides": [
          {
            "matcher": {
              "id": "byName",
              "options": "$ held"
            },
            "properties": [
              {
                "id": "color",
                "value": {
                  "fixedColor": "yellow",
                  "mode": "fixed"
                }
              }
            ]
          },
          {
            "matcher": {
              "id": "byName",
              "options": "$ estimated"
            },
            "properties": [
              {
                "id": "color",
                "value": {
                  "fixedColor": "dark-blue",
                  "mode": "fixed"
                }
              }
            ]
          }
        ]
      },
      "gridPos": {
        "h": 4,
        "w": 6,
        "x": 16,
        "y": 1
      },
      "id": 468,
      "links": [],
      "maxDataPoints": 100,
      "options": {
        "colorMode": "background",
        "graphMode": "area",
        "justifyMode": "auto",
        "orientation": "vertical",
        "reduceOptions": {
          "calcs": [
            "lastNotNull"
          ],
          "fields": "",
          "values": false
        },
        "text": {},
        "textMode": "auto"
      },
      "pluginVersion": "8.5.5",
      "targets": [
        {
          "datasource": {
            "type": "prometheus",
            "uid": "${DS_PROMETHEUS}"
          },
          "exemplar": true,
          "expr": "sum(storj_payout_currentMonth{type=~\"payout|held\",job=~\"$job.*\"}) / 100",
          "hide": false,
          "interval": "",
          "legendFormat": "$ total",
          "refId": "D"
        },
        {
          "datasource": {
            "type": "prometheus",
            "uid": "${DS_PROMETHEUS}"
          },
          "exemplar": true,
          "expr": "sum(storj_payout_currentMonth{type=~\"held\",job=~\"$job.*\"})/100",
          "hide": false,
          "interval": "",
          "legendFormat": "$ held",
          "refId": "B"
        },
        {
          "datasource": {
            "type": "prometheus",
            "uid": "${DS_PROMETHEUS}"
          },
          "exemplar": true,
          "expr": "((sum(storj_payout_currentMonth{type=~\"payout|held\",job=~\"$job.*\"})/100)/((day_of_month()-1)+(hour()/24)))*days_in_month()",
          "hide": false,
          "interval": "",
          "legendFormat": "$ estimated",
          "refId": "A"
        },
        {
          "datasource": {
            "type": "prometheus",
            "uid": "$datasource"
          },
          "editorMode": "code",
          "expr": "sum(storj_payout_currentMonth{type=~\"currentMonthExpectations\",job=~\"$job.*\"}) / 100",
          "hide": false,
          "legendFormat": "$ estimated (STORJ Calc)",
          "range": true,
          "refId": "C"
        }
      ],
      "title": "Payout summary",
      "type": "stat"
    },
    {
      "alert": {
        "alertRuleTags": {},
        "conditions": [
          {
            "evaluator": {
              "params": [
                7
              ],
              "type": "lt"
            },
            "operator": {
              "type": "and"
            },
            "query": {
              "params": [
                "A",
                "1m",
                "now"
              ]
            },
            "reducer": {
              "params": [],
              "type": "last"
            },
            "type": "query"
          }
        ],
        "executionErrorState": "alerting",
        "for": "30m",
        "frequency": "1m",
        "handler": 1,
        "message": "Storj Node Count < 7",
        "name": "Nodes Offline alert",
        "noDataState": "no_data",
        "notifications": [
          {
            "uid": "DllCdJxMz"
          }
        ]
      },
      "datasource": {
        "type": "prometheus",
        "uid": "${DS_PROMETHEUS}"
      },
      "description": "",
      "fieldConfig": {
        "defaults": {
          "color": {
            "mode": "palette-classic"
          },
          "custom": {
            "axisLabel": "",
            "axisPlacement": "auto",
            "barAlignment": 0,
            "drawStyle": "line",
            "fillOpacity": 10,
            "gradientMode": "none",
            "hideFrom": {
              "legend": false,
              "tooltip": false,
              "viz": false
            },
            "lineInterpolation": "linear",
            "lineWidth": 1,
            "pointSize": 5,
            "scaleDistribution": {
              "type": "linear"
            },
            "showPoints": "never",
            "spanNulls": false,
            "stacking": {
              "group": "A",
              "mode": "none"
            },
            "thresholdsStyle": {
              "mode": "line+area"
            }
          },
          "decimals": 0,
          "displayName": "node count",
          "mappings": [],
          "max": 7,
          "min": 0,
          "noValue": "0",
          "thresholds": {
            "mode": "absolute",
            "steps": [
              {
                "color": "red",
                "value": null
              },
              {
                "color": "transparent",
                "value": 7
              }
            ]
          },
          "unit": "short"
        },
        "overrides": []
      },
      "gridPos": {
        "h": 4,
        "w": 2,
        "x": 22,
        "y": 1
      },
      "id": 597,
      "options": {
        "legend": {
          "calcs": [],
          "displayMode": "hidden",
          "placement": "bottom"
        },
        "tooltip": {
          "mode": "multi",
          "sort": "none"
        }
      },
      "pluginVersion": "8.5.5",
      "targets": [
        {
          "datasource": {
            "type": "prometheus",
            "uid": "${DS_PROMETHEUS}"
          },
          "exemplar": true,
          "expr": "count(storj_node_info{type=\"nodeID\"})",
          "interval": "",
          "legendFormat": "",
          "refId": "A"
        }
      ],
      "thresholds": [
        {
          "colorMode": "critical",
          "op": "lt",
          "value": 7,
          "visible": true
        }
      ],
      "title": "Nodes Online",
      "type": "timeseries"
    },
    {
      "datasource": {
        "type": "prometheus",
        "uid": "${DS_PROMETHEUS}"
      },
      "description": "* DQ - Disqualified\n* SU - Suspended\n* UTD - Up to date",
      "fieldConfig": {
        "defaults": {
          "color": {
            "mode": "thresholds"
          },
          "custom": {
            "align": "center",
            "displayMode": "auto",
            "filterable": false,
            "inspect": false,
            "minWidth": 50
          },
          "decimals": 2,
          "mappings": [],
          "thresholds": {
            "mode": "absolute",
            "steps": [
              {
                "color": "green",
                "value": null
              },
              {
                "color": "red",
                "value": 90
              }
            ]
          },
          "unit": "none"
        },
        "overrides": [
          {
            "matcher": {
              "id": "byName",
              "options": "Disk % Used"
            },
            "properties": [
              {
                "id": "unit",
                "value": "short"
              },
              {
                "id": "decimals",
                "value": 2
              },
              {
                "id": "custom.displayMode",
                "value": "color-background"
              }
            ]
          },
          {
            "matcher": {
              "id": "byName",
              "options": "Net In"
            },
            "properties": [
              {
                "id": "unit",
                "value": "bytes"
              },
              {
                "id": "custom.displayMode",
                "value": "color-background"
              },
              {
                "id": "color",
                "value": {
                  "fixedColor": "#00388d",
                  "mode": "fixed"
                }
              }
            ]
          },
          {
            "matcher": {
              "id": "byName",
              "options": "Net Out"
            },
            "properties": [
              {
                "id": "unit",
                "value": "bytes"
              },
              {
                "id": "custom.displayMode",
                "value": "color-background"
              },
              {
                "id": "color",
                "value": {
                  "fixedColor": "#00388d",
                  "mode": "fixed"
                }
              }
            ]
          },
          {
            "matcher": {
              "id": "byName",
              "options": "Disk Total"
            },
            "properties": [
              {
                "id": "unit",
                "value": "decbytes"
              }
            ]
          },
          {
            "matcher": {
              "id": "byName",
              "options": "Disk Used"
            },
            "properties": [
              {
                "id": "unit",
                "value": "decbytes"
              }
            ]
          },
          {
            "matcher": {
              "id": "byName",
              "options": "Trash"
            },
            "properties": [
              {
                "id": "unit",
                "value": "decbytes"
              }
            ]
          },
          {
            "matcher": {
              "id": "byName",
              "options": "Version "
            },
            "properties": [
              {
                "id": "decimals",
                "value": 2
              }
            ]
          },
          {
            "matcher": {
              "id": "byName",
              "options": "Expected"
            },
            "properties": [
              {
                "id": "unit",
                "value": "currencyUSD"
              },
              {
                "id": "color",
                "value": {
                  "fixedColor": "#0b5b01",
                  "mode": "fixed"
                }
              },
              {
                "id": "custom.displayMode",
                "value": "color-background"
              }
            ]
          },
          {
            "matcher": {
              "id": "byName",
              "options": "Payout"
            },
            "properties": [
              {
                "id": "unit",
                "value": "currencyUSD"
              },
              {
                "id": "custom.displayMode",
                "value": "color-background"
              },
              {
                "id": "color",
                "value": {
                  "fixedColor": "#0b5b01",
                  "mode": "fixed"
                }
              }
            ]
          },
          {
            "matcher": {
              "id": "byName",
              "options": "Node Name"
            },
            "properties": [
              {
                "id": "custom.width",
                "value": 150
              },
              {
                "id": "custom.align",
                "value": "right"
              }
            ]
          },
          {
            "matcher": {
              "id": "byName",
              "options": "Held"
            },
            "properties": [
              {
                "id": "unit",
                "value": "currencyUSD"
              },
              {
                "id": "custom.displayMode",
                "value": "color-background"
              },
              {
                "id": "color",
                "value": {
                  "fixedColor": "#0b5b01",
                  "mode": "fixed"
                }
              }
            ]
          },
          {
            "matcher": {
              "id": "byName",
              "options": "Uptime"
            },
            "properties": [
              {
                "id": "custom.displayMode",
                "value": "color-background"
              },
              {
                "id": "thresholds",
                "value": {
                  "mode": "absolute",
                  "steps": [
                    {
                      "color": "red",
                      "value": null
                    },
                    {
                      "color": "#EAB839",
                      "value": 98
                    },
                    {
                      "color": "green",
                      "value": 99.8
                    }
                  ]
                }
              }
            ]
          },
          {
            "matcher": {
              "id": "byName",
              "options": "Audit"
            },
            "properties": [
              {
                "id": "custom.displayMode",
                "value": "color-background"
              },
              {
                "id": "thresholds",
                "value": {
                  "mode": "absolute",
                  "steps": [
                    {
                      "color": "red",
                      "value": null
                    },
                    {
                      "color": "#EAB839",
                      "value": 98
                    },
                    {
                      "color": "green",
                      "value": 99.8
                    }
                  ]
                }
              }
            ]
          },
          {
            "matcher": {
              "id": "byName",
              "options": "DQ"
            },
            "properties": [
              {
                "id": "custom.displayMode",
                "value": "color-background"
              },
              {
                "id": "thresholds",
                "value": {
                  "mode": "absolute",
                  "steps": [
                    {
                      "color": "green",
                      "value": null
                    },
                    {
                      "color": "red",
                      "value": 1e-90
                    }
                  ]
                }
              },
              {
                "id": "custom.minWidth",
                "value": 10
              }
            ]
          },
          {
            "matcher": {
              "id": "byName",
              "options": "SU"
            },
            "properties": [
              {
                "id": "custom.displayMode",
                "value": "color-background"
              },
              {
                "id": "thresholds",
                "value": {
                  "mode": "absolute",
                  "steps": [
                    {
                      "color": "green",
                      "value": null
                    },
                    {
                      "color": "red",
                      "value": 1e-9
                    }
                  ]
                }
              }
            ]
          },
          {
            "matcher": {
              "id": "byName",
              "options": "UTD"
            },
            "properties": [
              {
                "id": "mappings",
                "value": [
                  {
                    "options": {
                      "1": {
                        "index": 0,
                        "text": "✅"
                      }
                    },
                    "type": "value"
                  },
                  {
                    "options": {
                      "from": 0,
                      "result": {
                        "index": 1,
                        "text": "⛔"
                      },
                      "to": 0.9999999999999999
                    },
                    "type": "range"
                  }
                ]
              }
            ]
          }
        ]
      },
      "gridPos": {
        "h": 9,
        "w": 24,
        "x": 0,
        "y": 5
      },
      "id": 921,
      "options": {
        "footer": {
          "enablePagination": false,
          "fields": "",
          "reducer": [
            "sum"
          ],
          "show": false
        },
        "showHeader": true,
        "sortBy": [
          {
            "desc": true,
            "displayName": "Disk % Used"
          }
        ]
      },
      "pluginVersion": "8.5.5",
      "targets": [
        {
          "datasource": {
            "type": "prometheus",
            "uid": "${DS_PROMETHEUS}"
          },
          "editorMode": "code",
          "exemplar": false,
          "expr": "avg(storj_sat_audit{type=~\"score|auditScore\", job=~\"$job.*\"}) by(job) * 100",
          "format": "table",
          "hide": false,
          "instant": true,
          "interval": "",
          "legendFormat": "{{job}} | Audit",
          "range": false,
          "refId": "D"
        },
        {
          "datasource": {
            "type": "prometheus",
            "uid": "${DS_PROMETHEUS}"
          },
          "editorMode": "code",
          "exemplar": false,
          "expr": "sum(storj_total_diskspace{type=\"available\", job=~\"$job.*\"}) by(job)",
          "format": "table",
          "hide": false,
          "instant": true,
          "interval": "",
          "legendFormat": "{{job}} | Disk available",
          "range": false,
          "refId": "G"
        },
        {
          "datasource": {
            "type": "prometheus",
            "uid": "${DS_PROMETHEUS}"
          },
          "editorMode": "code",
          "exemplar": false,
          "expr": "sum(storj_total_diskspace{type=\"used\",  job=~\"$job.*\"}) by(job)",
          "format": "table",
          "hide": false,
          "instant": true,
          "interval": "",
          "legendFormat": "{{job}} | Disk used",
          "range": false,
          "refId": "E"
        },
        {
          "datasource": {
            "type": "prometheus",
            "uid": "${DS_PROMETHEUS}"
          },
          "editorMode": "code",
          "exemplar": false,
          "expr": "(sum(storj_total_diskspace{type=\"used\",  job=~\"$job.*\"}) by(job) / sum(storj_total_diskspace{type=\"available\",  job=~\"$job.*\"}) by(job) * 100)",
          "format": "table",
          "hide": false,
          "instant": true,
          "interval": "",
          "legendFormat": "{{job}} | Disk Percent",
          "range": false,
          "refId": "O"
        },
        {
          "datasource": {
            "type": "prometheus",
            "uid": "${DS_PROMETHEUS}"
          },
          "editorMode": "code",
          "exemplar": false,
          "expr": "sum(storj_total_diskspace{type=\"trash\", job=~\"$job.*\"}) by(job)",
          "format": "table",
          "hide": false,
          "instant": true,
          "interval": "",
          "legendFormat": "{{job}} | Trash",
          "range": false,
          "refId": "M"
        },
        {
          "datasource": {
            "type": "prometheus",
            "uid": "${DS_PROMETHEUS}"
          },
          "editorMode": "code",
          "exemplar": false,
          "expr": "sum(storj_sat_month_ingress{job=~\"$job.*\"}) by(job)",
          "format": "table",
          "hide": false,
          "instant": true,
          "interval": "",
          "legendFormat": "{{job}} | In",
          "range": false,
          "refId": "B"
        },
        {
          "datasource": {
            "type": "prometheus",
            "uid": "${DS_PROMETHEUS}"
          },
          "editorMode": "code",
          "exemplar": false,
          "expr": "sum(storj_sat_month_egress{job=~\"$job.*\"}) by(job)",
          "format": "table",
          "hide": false,
          "instant": true,
          "interval": "",
          "intervalFactor": 1,
          "legendFormat": "{{job}} | Out",
          "range": false,
          "refId": "A"
        },
        {
          "datasource": {
            "type": "prometheus",
            "uid": "${DS_PROMETHEUS}"
          },
          "editorMode": "code",
          "exemplar": false,
          "expr": "sum(storj_payout_currentMonth{type=~\"payout|held\", job=~\"$job.*\"}) by(job) / 100",
          "format": "table",
          "hide": false,
          "instant": true,
          "interval": "",
          "legendFormat": "{{job}} | Earnings",
          "range": false,
          "refId": "H"
        },
        {
          "datasource": {
            "type": "prometheus",
            "uid": "${DS_PROMETHEUS}"
          },
          "editorMode": "code",
          "exemplar": false,
          "expr": "sum(storj_payout_currentMonth{type=~\"currentMonthExpectations\", job=~\"$job.*\"}) by(job) / 100",
          "format": "table",
          "hide": false,
          "instant": true,
          "interval": "",
          "legendFormat": "{{job}} | Payout_expectations",
          "range": false,
          "refId": "N"
        },
        {
          "datasource": {
            "type": "prometheus",
            "uid": "${DS_PROMETHEUS}"
          },
          "editorMode": "code",
          "exemplar": false,
          "expr": "sum(storj_payout_currentMonth{type=~\"held\", job=~\"$job\"}) by(job) / 100",
          "format": "table",
          "hide": false,
          "instant": true,
          "interval": "",
          "legendFormat": "{{job}} | Held",
          "range": false,
          "refId": "J"
        },
        {
          "datasource": {
            "type": "prometheus",
            "uid": "${DS_PROMETHEUS}"
          },
          "editorMode": "code",
          "exemplar": false,
          "expr": "avg (storj_sat_summary{type=\"disqualified\",job=~\"$job.*\"}) by(job)",
          "format": "table",
          "hide": false,
          "instant": true,
          "interval": "",
          "legendFormat": "{{job}} | Disqualified",
          "range": false,
          "refId": "K"
        },
        {
          "datasource": {
            "type": "prometheus",
            "uid": "${DS_PROMETHEUS}"
          },
          "editorMode": "code",
          "exemplar": false,
          "expr": "avg (storj_sat_summary{type=\"suspended\",job=~\"$job.*\"}) by(job)",
          "format": "table",
          "hide": false,
          "instant": true,
          "interval": "",
          "legendFormat": "{{job}} | Suspended",
          "range": false,
          "refId": "L"
        },
        {
          "datasource": {
            "type": "prometheus",
            "uid": "${DS_PROMETHEUS}"
          },
          "editorMode": "code",
          "exemplar": false,
          "expr": "avg (storj_node_info{job=~\"$job.*\", type=\"upToDate\"}) by (job)",
          "format": "table",
          "hide": false,
          "instant": true,
          "interval": "",
          "legendFormat": "{{job}} | UpToDate",
          "range": false,
          "refId": "F"
        },
        {
          "datasource": {
            "type": "prometheus",
            "uid": "${DS_PROMETHEUS}"
          },
          "editorMode": "code",
          "exemplar": false,
          "expr": "avg(storj_sat_summary{type=\"onlineScore\", job=~\"$job.*\"} or storj_sat_audit{type=\"onlineScore\", job=~\"$job.*\", url!=\"europe-north-1.tardigrade.io:7777\", url!=\"us2.storj.io:7777\"}) by(job) * 100",
          "format": "table",
          "hide": false,
          "instant": true,
          "interval": "",
          "legendFormat": "{{job}} | Uptime",
          "range": false,
          "refId": "C"
        },
        {
          "datasource": {
            "type": "prometheus",
            "uid": "${DS_PROMETHEUS}"
          },
          "editorMode": "code",
          "exemplar": false,
          "expr": "storj_node_info{job=~\"$job.*\", type=\"version\"}",
          "format": "table",
          "hide": false,
          "instant": true,
          "interval": "",
          "legendFormat": "{{job}} | Version | {{version}}",
          "refId": "I"
        }
      ],
      "title": "Node summary table",
      "transformations": [
        {
          "id": "seriesToColumns",
          "options": {
            "byField": "job"
          }
        },
        {
          "id": "organize",
          "options": {
            "excludeByName": {
              "Time": true,
              "Time 1": true,
              "Time 10": true,
              "Time 11": true,
              "Time 12": true,
              "Time 13": true,
              "Time 14": true,
              "Time 2": true,
              "Time 3": true,
              "Time 4": true,
              "Time 5": true,
              "Time 6": true,
              "Time 7": true,
              "Time 8": true,
              "Time 9": true,
              "Value #I": true,
              "__name__": true,
              "instance": true,
              "job 1": false,
              "job 2": true,
              "type": true,
              "version": false
            },
            "indexByName": {},
            "renameByName": {
              "Time 1": "",
              "Time 10": "",
              "Time 13": "",
              "Time 2": "",
              "Time 3": "",
              "Time 4": "",
              "Time 5": "",
              "Time 6": "",
              "Time 7": "",
              "Time 8": "",
              "Time 9": "",
              "Value #A": "Net Out",
              "Value #B": "Net In",
              "Value #C": "Uptime",
              "Value #D": "Audit",
              "Value #E": "Disk Used",
              "Value #F": "UTD",
              "Value #G": "Disk Total",
              "Value #H": "Payout",
              "Value #I": "",
              "Value #J": "Held",
              "Value #K": "DQ",
              "Value #L": "SU",
              "Value #M": "Trash",
              "Value #N": "Expected",
              "Value #O": "Disk % Used",
              "job": "Node Name",
              "job 1": "Node Name",
              "job 2": "",
              "version": "Version"
            }
          }
        },
        {
          "id": "groupBy",
          "options": {
            "fields": {
              "Value #A": {
                "aggregations": []
              },
              "Value #B": {
                "aggregations": []
              },
              "job 1": {
                "aggregations": []
              }
            }
          }
        }
      ],
      "type": "table"
    },
    {
      "datasource": {
        "type": "prometheus",
        "uid": "${DS_PROMETHEUS}"
      },
      "fieldConfig": {
        "defaults": {
          "color": {
            "mode": "thresholds"
          },
          "mappings": [],
          "min": 0,
          "thresholds": {
            "mode": "absolute",
            "steps": [
              {
                "color": "red",
                "value": null
              },
              {
                "color": "#EAB839",
                "value": 1000000
              },
              {
                "color": "green",
                "value": 5000000
              }
            ]
          },
          "unit": "bps"
        },
        "overrides": []
      },
      "gridPos": {
        "h": 8,
        "w": 7,
        "x": 0,
        "y": 14
      },
      "id": 673,
      "options": {
        "colorMode": "value",
        "graphMode": "area",
        "justifyMode": "auto",
        "orientation": "auto",
        "reduceOptions": {
          "calcs": [
            "lastNotNull"
          ],
          "fields": "",
          "values": false
        },
        "textMode": "auto"
      },
      "pluginVersion": "8.5.5",
      "targets": [
        {
          "datasource": {
            "type": "prometheus",
            "uid": "${DS_PROMETHEUS}"
          },
          "editorMode": "code",
          "expr": "avg(sum(rate(storj_sat_month_egress{job=~\"$job.*\"}[5m])) * 8)",
          "legendFormat": "Egress",
          "range": true,
          "refId": "A"
        },
        {
          "datasource": {
            "type": "prometheus",
            "uid": "${DS_PROMETHEUS}"
          },
          "editorMode": "code",
          "expr": "avg(sum(rate(storj_sat_month_ingress{job=~\"$job.*\"}[5m])) * 8)",
          "hide": false,
          "legendFormat": "Ingress",
          "range": true,
          "refId": "B"
        }
      ],
      "title": "Total I/O (Average)",
      "type": "stat"
    },
    {
      "datasource": {
        "type": "prometheus",
        "uid": "${DS_PROMETHEUS}"
      },
      "fieldConfig": {
        "defaults": {
          "color": {
            "mode": "thresholds"
          },
          "mappings": [],
          "min": 0,
          "thresholds": {
            "mode": "absolute",
            "steps": [
              {
                "color": "red",
                "value": null
              },
              {
                "color": "#EAB839",
                "value": 500000000000
              },
              {
                "color": "green",
                "value": 1000000000000
              }
            ]
          },
          "unit": "decbytes"
        },
        "overrides": []
      },
      "gridPos": {
        "h": 8,
        "w": 4,
        "x": 7,
        "y": 14
      },
      "id": 860,
      "options": {
        "colorMode": "value",
        "graphMode": "area",
        "justifyMode": "auto",
        "orientation": "auto",
        "reduceOptions": {
          "calcs": [
            "diff"
          ],
          "fields": "",
          "values": false
        },
        "textMode": "auto"
      },
      "pluginVersion": "8.5.5",
      "targets": [
        {
          "datasource": {
            "type": "prometheus",
            "uid": "${DS_PROMETHEUS}"
          },
          "editorMode": "code",
          "expr": "(sum(storj_total_diskspace{type=\"used\", job=~\"$job.*\"}))",
          "legendFormat": "{{job}} ",
          "range": true,
          "refId": "A"
        }
      ],
      "timeFrom": "30d",
      "title": "Total Change in Data (30d)",
      "type": "stat"
    },
    {
      "datasource": {
        "type": "prometheus",
        "uid": "$datasource"
      },
      "fieldConfig": {
        "defaults": {
          "color": {
            "mode": "palette-classic"
          },
          "custom": {
            "axisLabel": "Rate-in (-) / Rate-out (+)",
            "axisPlacement": "auto",
            "barAlignment": 0,
            "drawStyle": "line",
            "fillOpacity": 70,
            "gradientMode": "opacity",
            "hideFrom": {
              "legend": false,
              "tooltip": false,
              "viz": false
            },
            "lineInterpolation": "linear",
            "lineWidth": 1,
            "pointSize": 5,
            "scaleDistribution": {
              "type": "linear"
            },
            "showPoints": "never",
            "spanNulls": true,
            "stacking": {
              "group": "A",
              "mode": "none"
            },
            "thresholdsStyle": {
              "mode": "off"
            }
          },
          "links": [],
          "mappings": [],
          "thresholds": {
            "mode": "absolute",
            "steps": [
              {
                "color": "green",
                "value": null
              },
              {
                "color": "red",
                "value": 80
              }
            ]
          },
          "unit": "bps"
        },
        "overrides": [
          {
            "matcher": {
              "id": "byRegexp",
              "options": "/RateOut/"
            },
            "properties": [
              {
                "id": "color",
                "value": {
                  "fixedColor": "#96D98D",
                  "mode": "fixed"
                }
              },
              {
                "id": "custom.stacking",
                "value": {
                  "group": "A",
                  "mode": "normal"
                }
              }
            ]
          },
          {
            "matcher": {
              "id": "byRegexp",
              "options": "/RateIn/"
            },
            "properties": [
              {
                "id": "color",
                "value": {
                  "fixedColor": "#FFB357",
                  "mode": "fixed"
                }
              },
              {
                "id": "custom.stacking",
                "value": {
                  "group": "B",
                  "mode": "normal"
                }
              },
              {
                "id": "custom.transform",
                "value": "negative-Y"
              }
            ]
          },
          {
            "matcher": {
              "id": "byName",
              "options": "0"
            },
            "properties": [
              {
                "id": "color",
                "value": {
                  "fixedColor": "rgb(4, 4, 4)",
                  "mode": "fixed"
                }
              }
            ]
          }
        ]
      },
      "gridPos": {
        "h": 8,
        "w": 13,
        "x": 11,
        "y": 14
      },
      "id": 297,
      "interval": "",
      "options": {
        "legend": {
          "calcs": [],
          "displayMode": "hidden",
          "placement": "bottom"
        },
        "tooltip": {
          "mode": "multi",
          "sort": "desc"
        }
      },
      "pluginVersion": "8.5.0",
      "targets": [
        {
          "datasource": {
            "type": "prometheus",
            "uid": "${DS_PROMETHEUS}"
          },
          "expr": "sum(rate(storj_sat_month_egress{job=~\"$job.*\"}[5m])) by(job) * 8",
          "format": "time_series",
          "hide": false,
          "instant": false,
          "interval": "",
          "intervalFactor": 4,
          "legendFormat": "RateOut {{job}}",
          "refId": "A"
        },
        {
          "datasource": {
            "type": "prometheus",
            "uid": "${DS_PROMETHEUS}"
          },
          "expr": "sum(rate(storj_sat_month_ingress{job=~\"$job.*\"}[5m])) by(job) * 8",
          "hide": false,
          "interval": "",
          "intervalFactor": 4,
          "legendFormat": "RateIn {{job}}",
          "refId": "B"
        },
        {
          "datasource": {
            "type": "prometheus",
            "uid": "${DS_PROMETHEUS}"
          },
          "expr": "0",
          "interval": "",
          "legendFormat": "0",
          "refId": "E"
        }
      ],
      "title": "Net IO by node (stacked)",
      "type": "timeseries"
    },
    {
      "datasource": {
        "type": "prometheus",
        "uid": "$datasource"
      },
      "fieldConfig": {
        "defaults": {
          "color": {
            "mode": "palette-classic"
          },
          "custom": {
            "axisLabel": "Sum-in (-) / Sum-out (+)",
            "axisPlacement": "auto",
            "barAlignment": 0,
            "drawStyle": "line",
            "fillOpacity": 70,
            "gradientMode": "opacity",
            "hideFrom": {
              "legend": false,
              "tooltip": false,
              "viz": false
            },
            "lineInterpolation": "linear",
            "lineWidth": 1,
            "pointSize": 5,
            "scaleDistribution": {
              "type": "linear"
            },
            "showPoints": "never",
            "spanNulls": true,
            "stacking": {
              "group": "A",
              "mode": "none"
            },
            "thresholdsStyle": {
              "mode": "off"
            }
          },
          "links": [],
          "mappings": [],
          "thresholds": {
            "mode": "absolute",
            "steps": [
              {
                "color": "green",
                "value": null
              },
              {
                "color": "red",
                "value": 80
              }
            ]
          },
          "unit": "decbytes"
        },
        "overrides": [
          {
            "matcher": {
              "id": "byRegexp",
              "options": "/RateOut/"
            },
            "properties": [
              {
                "id": "custom.stacking",
                "value": {
                  "group": "A",
                  "mode": "normal"
                }
              },
              {
                "id": "unit",
                "value": "bps"
              },
              {
                "id": "custom.axisLabel",
                "value": "Rate-in (-) / Rate-out (+)"
              }
            ]
          },
          {
            "matcher": {
              "id": "byRegexp",
              "options": "/RateIn/"
            },
            "properties": [
              {
                "id": "custom.stacking",
                "value": {
                  "group": "B",
                  "mode": "normal"
                }
              },
              {
                "id": "custom.transform",
                "value": "negative-Y"
              },
              {
                "id": "unit",
                "value": "bps"
              },
              {
                "id": "custom.axisLabel",
                "value": "Rate-in (-) / Rate-out (+)"
              }
            ]
          },
          {
            "matcher": {
              "id": "byRegexp",
              "options": "/SumOut/"
            },
            "properties": [
              {
                "id": "custom.fillOpacity",
                "value": 20
              },
              {
                "id": "custom.lineWidth",
                "value": 0
              },
              {
                "id": "custom.stacking",
                "value": {
                  "group": "C",
                  "mode": "normal"
                }
              }
            ]
          },
          {
            "matcher": {
              "id": "byRegexp",
              "options": "/SumIn/"
            },
            "properties": [
              {
                "id": "custom.fillOpacity",
                "value": 20
              },
              {
                "id": "custom.lineWidth",
                "value": 0
              },
              {
                "id": "custom.stacking",
                "value": {
                  "group": "D",
                  "mode": "normal"
                }
              },
              {
                "id": "custom.transform",
                "value": "negative-Y"
              }
            ]
          }
        ]
      },
      "gridPos": {
        "h": 6,
        "w": 12,
        "x": 0,
        "y": 22
      },
      "id": 299,
      "interval": "",
      "options": {
        "legend": {
          "calcs": [],
          "displayMode": "hidden",
          "placement": "bottom"
        },
        "tooltip": {
          "mode": "multi",
          "sort": "desc"
        }
      },
      "pluginVersion": "8.5.0",
      "targets": [
        {
          "datasource": {
            "type": "prometheus",
            "uid": "${DS_PROMETHEUS}"
          },
          "expr": "sum(storj_sat_month_egress{type!=\"usage\", job=~\"$job.*\"}) by(type,job)",
          "format": "time_series",
          "hide": false,
          "instant": false,
          "interval": "",
          "intervalFactor": 1,
          "legendFormat": "SumOut-{{type}}-{{job}}",
          "refId": "C"
        },
        {
          "datasource": {
            "type": "prometheus",
            "uid": "${DS_PROMETHEUS}"
          },
          "expr": "sum(storj_sat_month_ingress{type!=\"usage\", job=~\"$job.*\"}) by(type,job)",
          "format": "time_series",
          "hide": false,
          "interval": "",
          "legendFormat": "SumIn-{{type}}-{{job}}",
          "refId": "D"
        },
        {
          "datasource": {
            "type": "prometheus",
            "uid": "${DS_PROMETHEUS}"
          },
          "expr": "sum(rate(storj_sat_month_egress{type!=\"usage\", job=~\"$job.*\"}[5m])) by(type,job) * 8",
          "format": "time_series",
          "hide": false,
          "instant": false,
          "interval": "",
          "intervalFactor": 4,
          "legendFormat": "RateOut-{{type}}-{{job}}",
          "refId": "A"
        },
        {
          "datasource": {
            "type": "prometheus",
            "uid": "${DS_PROMETHEUS}"
          },
          "expr": "sum(rate(storj_sat_month_ingress{type!=\"usage\", job=~\"$job.*\"}[5m])) by(type,job) * 8",
          "hide": false,
          "interval": "",
          "intervalFactor": 4,
          "legendFormat": "RateIn-{{type}}-{{job}}",
          "refId": "B"
        }
      ],
      "title": "Audit/Repair IO/sum by node (stacked)",
      "type": "timeseries"
    },
    {
      "datasource": {
        "type": "prometheus",
        "uid": "$datasource"
      },
      "fieldConfig": {
        "defaults": {
          "color": {
            "mode": "palette-classic"
          },
          "custom": {
            "axisLabel": "Rate-in (-) / Rate-out (+)",
            "axisPlacement": "auto",
            "barAlignment": 0,
            "drawStyle": "line",
            "fillOpacity": 80,
            "gradientMode": "opacity",
            "hideFrom": {
              "legend": false,
              "tooltip": false,
              "viz": false
            },
            "lineInterpolation": "linear",
            "lineWidth": 1,
            "pointSize": 5,
            "scaleDistribution": {
              "type": "linear"
            },
            "showPoints": "never",
            "spanNulls": true,
            "stacking": {
              "group": "A",
              "mode": "normal"
            },
            "thresholdsStyle": {
              "mode": "off"
            }
          },
          "decimals": 2,
          "links": [],
          "mappings": [],
          "thresholds": {
            "mode": "absolute",
            "steps": [
              {
                "color": "green",
                "value": null
              },
              {
                "color": "red",
                "value": 80
              }
            ]
          },
          "unit": "bps"
        },
        "overrides": [
          {
            "matcher": {
              "id": "byRegexp",
              "options": "/DiskRate/"
            },
            "properties": [
              {
                "id": "color",
                "value": {
                  "fixedColor": "#FFB357",
                  "mode": "fixed"
                }
              }
            ]
          }
        ]
      },
      "gridPos": {
        "h": 6,
        "w": 12,
        "x": 12,
        "y": 22
      },
      "id": 298,
      "interval": "",
      "options": {
        "legend": {
          "calcs": [],
          "displayMode": "hidden",
          "placement": "bottom"
        },
        "tooltip": {
          "mode": "multi",
          "sort": "desc"
        }
      },
      "pluginVersion": "8.5.0",
      "targets": [
        {
          "datasource": {
            "type": "prometheus",
            "uid": "${DS_PROMETHEUS}"
          },
          "expr": "sum(delta(storj_total_diskspace{type=\"used\", job=~\"$job.*\"}[5m])) by(job) * 8 / 300",
          "format": "time_series",
          "hide": false,
          "instant": false,
          "interval": "",
          "intervalFactor": 4,
          "legendFormat": "DiskRate {{job}}",
          "refId": "B"
        }
      ],
      "title": "Storage IO by node (stacked)",
      "type": "timeseries"
    },
    {
      "collapsed": false,
      "datasource": {
        "uid": "$datasource"
      },
      "gridPos": {
        "h": 1,
        "w": 24,
        "x": 0,
        "y": 28
      },
      "id": 42,
      "panels": [],
      "repeat": "job",
      "title": "$job details",
      "type": "row"
    },
    {
      "datasource": {
        "type": "prometheus",
        "uid": "$datasource"
      },
      "description": "* DQ - Disqualified\n* SU - Suspended",
      "fieldConfig": {
        "defaults": {
          "color": {
            "mode": "thresholds"
          },
          "custom": {
            "align": "center",
            "displayMode": "auto",
            "inspect": false,
            "minWidth": 0,
            "width": 0
          },
          "mappings": [],
          "thresholds": {
            "mode": "absolute",
            "steps": [
              {
                "color": "green",
                "value": null
              },
              {
                "color": "red",
                "value": 80
              }
            ]
          }
        },
        "overrides": [
          {
            "matcher": {
              "id": "byName",
              "options": "Satellite"
            },
            "properties": [
              {
                "id": "mappings",
                "value": [
                  {
                    "options": {
                      "pattern": "(.*)\\..*\\.io.*",
                      "result": {
                        "color": "red",
                        "index": 0,
                        "text": "$1"
                      }
                    },
                    "type": "regex"
                  }
                ]
              },
              {
                "id": "custom.align",
                "value": "right"
              }
            ]
          },
          {
            "matcher": {
              "id": "byName",
              "options": "Audit"
            },
            "properties": [
              {
                "id": "unit",
                "value": "percent"
              },
              {
                "id": "decimals",
                "value": 1
              },
              {
                "id": "custom.displayMode",
                "value": "color-background"
              },
              {
                "id": "thresholds",
                "value": {
                  "mode": "absolute",
                  "steps": [
                    {
                      "color": "red",
                      "value": null
                    },
                    {
                      "color": "#EAB839",
                      "value": 98
                    },
                    {
                      "color": "green",
                      "value": 99.8
                    }
                  ]
                }
              }
            ]
          },
          {
            "matcher": {
              "id": "byName",
              "options": "DQ"
            },
            "properties": [
              {
                "id": "custom.displayMode",
                "value": "color-background"
              },
              {
                "id": "thresholds",
                "value": {
                  "mode": "absolute",
                  "steps": [
                    {
                      "color": "green",
                      "value": null
                    },
                    {
                      "color": "red",
                      "value": 1e-9
                    }
                  ]
                }
              }
            ]
          },
          {
            "matcher": {
              "id": "byName",
              "options": "Net In"
            },
            "properties": [
              {
                "id": "unit",
                "value": "bytes"
              },
              {
                "id": "custom.displayMode",
                "value": "color-background"
              },
              {
                "id": "color",
                "value": {
                  "fixedColor": "#00388d",
                  "mode": "fixed"
                }
              }
            ]
          },
          {
            "matcher": {
              "id": "byName",
              "options": "Net Out"
            },
            "properties": [
              {
                "id": "unit",
                "value": "bytes"
              },
              {
                "id": "color",
                "value": {
                  "fixedColor": "#00388d",
                  "mode": "fixed"
                }
              },
              {
                "id": "custom.displayMode",
                "value": "color-background"
              }
            ]
          },
          {
            "matcher": {
              "id": "byName",
              "options": "Payout"
            },
            "properties": [
              {
                "id": "unit",
                "value": "currencyUSD"
              },
              {
                "id": "custom.displayMode",
                "value": "color-background"
              },
              {
                "id": "color",
                "value": {
                  "fixedColor": "#0b5b01",
                  "mode": "fixed"
                }
              }
            ]
          },
          {
            "matcher": {
              "id": "byName",
              "options": "SU"
            },
            "properties": [
              {
                "id": "custom.displayMode",
                "value": "color-background"
              },
              {
                "id": "thresholds",
                "value": {
                  "mode": "absolute",
                  "steps": [
                    {
                      "color": "green",
                      "value": null
                    },
                    {
                      "color": "red",
                      "value": 1e-9
                    }
                  ]
                }
              }
            ]
          },
          {
            "matcher": {
              "id": "byName",
              "options": "Uptime"
            },
            "properties": [
              {
                "id": "decimals",
                "value": 2
              },
              {
                "id": "custom.displayMode",
                "value": "color-background"
              },
              {
                "id": "thresholds",
                "value": {
                  "mode": "absolute",
                  "steps": [
                    {
                      "color": "red",
                      "value": null
                    },
                    {
                      "color": "#EAB839",
                      "value": 98
                    },
                    {
                      "color": "green",
                      "value": 99.8
                    }
                  ]
                }
              }
            ]
          }
        ]
      },
      "gridPos": {
        "h": 7,
        "w": 12,
        "x": 0,
        "y": 29
      },
      "id": 982,
      "options": {
        "footer": {
          "fields": "",
          "reducer": [
            "sum"
          ],
          "show": false
        },
        "showHeader": true,
        "sortBy": [
          {
            "desc": false,
            "displayName": "Satellite"
          }
        ]
      },
      "pluginVersion": "8.5.5",
      "targets": [
        {
          "datasource": {
            "type": "prometheus",
            "uid": "${DS_PROMETHEUS}"
          },
          "editorMode": "code",
          "exemplar": false,
          "expr": "avg(storj_sat_audit{type=~\"score|auditScore\",job=~\"$job.*\", url!=\"us2.storj.io:7777\", url!=\"europe-north-1.tardigrade.io:7777\"}) by(url) * 100",
          "format": "table",
          "hide": false,
          "instant": true,
          "legendFormat": "{{url}} | Audit",
          "range": false,
          "refId": "D"
        },
        {
          "datasource": {
            "type": "prometheus",
            "uid": "${DS_PROMETHEUS}"
          },
          "editorMode": "code",
          "exemplar": false,
          "expr": "sum(storj_sat_summary{type=\"disqualified\",job=~\"$job.*\", url!=\"us2.storj.io:7777\", url!=\"europe-north-1.tardigrade.io:7777\"}) by (url)",
          "format": "table",
          "instant": true,
          "legendFormat": "{{url}} | Disqualified",
          "range": false,
          "refId": "F"
        },
        {
          "datasource": {
            "type": "prometheus",
            "uid": "${DS_PROMETHEUS}"
          },
          "editorMode": "code",
          "exemplar": false,
          "expr": "sum(storj_sat_month_ingress{job=~\"$job.*\"}) by(url)",
          "format": "table",
          "hide": false,
          "instant": true,
          "legendFormat": "{{url}} | In",
          "range": false,
          "refId": "B"
        },
        {
          "datasource": {
            "type": "prometheus",
            "uid": "${DS_PROMETHEUS}"
          },
          "editorMode": "code",
          "exemplar": false,
          "expr": "sum(storj_sat_month_egress{job=~\"$job.*\"}) by(url)",
          "format": "table",
          "hide": false,
          "instant": true,
          "interval": "",
          "intervalFactor": 1,
          "legendFormat": "{{url}} | Out",
          "range": false,
          "refId": "A"
        },
        {
          "datasource": {
            "type": "prometheus",
            "uid": "${DS_PROMETHEUS}"
          },
          "editorMode": "code",
          "exemplar": false,
          "expr": "(sum(storj_sat_summary{type=\"storageSummary\",job=~\"$job.*\"}) by(url) / (30 * 24) * 1.5  / 1000^4) + (sum(storj_sat_month_egress{job=~\"$job.*\"}) by(url) / 1000^4 * 20)",
          "format": "table",
          "instant": true,
          "interval": "",
          "legendFormat": "{{url}} | Payout",
          "range": false,
          "refId": "H"
        },
        {
          "datasource": {
            "type": "prometheus",
            "uid": "${DS_PROMETHEUS}"
          },
          "editorMode": "code",
          "exemplar": false,
          "expr": "sum(storj_sat_audit{type=\"successCount\",job=~\"$job.*\"}) by (url)",
          "format": "table",
          "instant": true,
          "legendFormat": "{{url}} | Vetting",
          "range": false,
          "refId": "E"
        },
        {
          "datasource": {
            "type": "prometheus",
            "uid": "${DS_PROMETHEUS}"
          },
          "editorMode": "code",
          "exemplar": false,
          "expr": "sum(storj_sat_summary{type=\"suspended\",job=~\"$job.*\", url!=\"us2.storj.io:7777\", url!=\"europe-north-1.tardigrade.io:7777\"}) by (url)",
          "format": "table",
          "instant": true,
          "legendFormat": "{{url}} | Suspended",
          "range": false,
          "refId": "G"
        },
        {
          "datasource": {
            "type": "prometheus",
            "uid": "${DS_PROMETHEUS}"
          },
          "editorMode": "code",
          "exemplar": false,
          "expr": "avg(storj_sat_summary{type=\"onlineScore\", job=~\"$job.*\"} or storj_sat_audit{type=\"onlineScore\", job=~\"$job.*\", url!=\"us2.storj.io:7777\", url!=\"europe-north-1.tardigrade.io:7777\"}) by(url) * 100",
          "format": "table",
          "hide": false,
          "instant": true,
          "interval": "",
          "legendFormat": "{{url}} | Uptime",
          "range": false,
          "refId": "C"
        }
      ],
      "title": "$job - Satellite summary table (monthly)",
      "transformations": [
        {
          "id": "seriesToColumns",
          "options": {
            "byField": "url"
          }
        },
        {
          "id": "organize",
          "options": {
            "excludeByName": {
              "Time 1": true,
              "Time 2": true,
              "Time 3": true,
              "Time 4": true,
              "Time 5": true,
              "Time 6": true,
              "Time 7": true
            },
            "indexByName": {},
            "renameByName": {
              "Time 1": "",
              "Time 3": "",
              "Time 7": "",
              "Value #A": "Net Out",
              "Value #B": "Net In",
              "Value #C": "Uptime",
              "Value #D": "Audit",
              "Value #F": "DQ",
              "Value #G": "SU",
              "Value #H": "Payout",
              "url": "Satellite"
            }
          }
        }
      ],
      "type": "table"
    },
    {
      "datasource": {
        "type": "prometheus",
        "uid": "$datasource"
      },
      "description": "",
      "fieldConfig": {
        "defaults": {
          "color": {
            "mode": "palette-classic"
          },
          "custom": {
            "axisLabel": "Sum-in (-) / Sum-out (+)",
            "axisPlacement": "auto",
            "barAlignment": 0,
            "drawStyle": "line",
            "fillOpacity": 70,
            "gradientMode": "opacity",
            "hideFrom": {
              "legend": false,
              "tooltip": false,
              "viz": false
            },
            "lineInterpolation": "linear",
            "lineWidth": 1,
            "pointSize": 5,
            "scaleDistribution": {
              "type": "linear"
            },
            "showPoints": "never",
            "spanNulls": true,
            "stacking": {
              "group": "A",
              "mode": "none"
            },
            "thresholdsStyle": {
              "mode": "off"
            }
          },
          "links": [],
          "mappings": [],
          "thresholds": {
            "mode": "absolute",
            "steps": [
              {
                "color": "green",
                "value": null
              },
              {
                "color": "red",
                "value": 80
              }
            ]
          },
          "unit": "decbytes"
        },
        "overrides": [
          {
            "matcher": {
              "id": "byRegexp",
              "options": "/RateOut/"
            },
            "properties": [
              {
                "id": "color",
                "value": {
                  "fixedColor": "#96D98D",
                  "mode": "fixed"
                }
              },
              {
                "id": "custom.stacking",
                "value": {
                  "group": "A",
                  "mode": "normal"
                }
              },
              {
                "id": "unit",
                "value": "bps"
              },
              {
                "id": "custom.axisLabel",
                "value": "Rate-in (-) / Rate-out (+)"
              }
            ]
          },
          {
            "matcher": {
              "id": "byRegexp",
              "options": "/RateIn/"
            },
            "properties": [
              {
                "id": "color",
                "value": {
                  "fixedColor": "#FFCB7D",
                  "mode": "fixed"
                }
              },
              {
                "id": "custom.stacking",
                "value": {
                  "group": "B",
                  "mode": "normal"
                }
              },
              {
                "id": "custom.transform",
                "value": "negative-Y"
              },
              {
                "id": "unit",
                "value": "bps"
              },
              {
                "id": "custom.axisLabel",
                "value": "Rate-in (-) / Rate-out (+)"
              }
            ]
          },
          {
            "matcher": {
              "id": "byRegexp",
              "options": "/SumOut/"
            },
            "properties": [
              {
                "id": "color",
                "value": {
                  "fixedColor": "#37872D",
                  "mode": "fixed"
                }
              },
              {
                "id": "custom.fillOpacity",
                "value": 20
              },
              {
                "id": "custom.lineWidth",
                "value": 0
              },
              {
                "id": "custom.stacking",
                "value": {
                  "group": "C",
                  "mode": "normal"
                }
              }
            ]
          },
          {
            "matcher": {
              "id": "byRegexp",
              "options": "/SumIn/"
            },
            "properties": [
              {
                "id": "color",
                "value": {
                  "fixedColor": "#FFB357",
                  "mode": "fixed"
                }
              },
              {
                "id": "custom.fillOpacity",
                "value": 20
              },
              {
                "id": "custom.lineWidth",
                "value": 0
              },
              {
                "id": "custom.stacking",
                "value": {
                  "group": "D",
                  "mode": "normal"
                }
              },
              {
                "id": "custom.transform",
                "value": "negative-Y"
              }
            ]
          }
        ]
      },
      "gridPos": {
        "h": 7,
        "w": 12,
        "x": 12,
        "y": 29
      },
      "id": 393,
      "interval": "",
      "options": {
        "legend": {
          "calcs": [],
          "displayMode": "hidden",
          "placement": "right"
        },
        "tooltip": {
          "mode": "multi",
          "sort": "desc"
        }
      },
      "pluginVersion": "8.5.0",
      "repeatDirection": "v",
      "targets": [
        {
          "datasource": {
            "type": "prometheus",
            "uid": "${DS_PROMETHEUS}"
          },
          "expr": "sum(irate(storj_sat_month_egress{job=~\"$job.*\"}[5m])) * 8",
          "format": "time_series",
          "hide": false,
          "instant": false,
          "interval": "",
          "intervalFactor": 4,
          "legendFormat": "RateOut {{job}}",
          "refId": "A"
        },
        {
          "datasource": {
            "type": "prometheus",
            "uid": "${DS_PROMETHEUS}"
          },
          "expr": "sum(irate(storj_sat_month_ingress{job=~\"$job.*\"}[5m])) * 8",
          "hide": false,
          "interval": "",
          "intervalFactor": 4,
          "legendFormat": "RateIn {{job}}",
          "refId": "B"
        },
        {
          "datasource": {
            "type": "prometheus",
            "uid": "${DS_PROMETHEUS}"
          },
          "expr": "sum(storj_sat_month_egress{job=~\"$job.*\"})",
          "format": "time_series",
          "hide": false,
          "instant": false,
          "intervalFactor": 1,
          "legendFormat": "SumOut {{job}}",
          "refId": "C"
        },
        {
          "datasource": {
            "type": "prometheus",
            "uid": "${DS_PROMETHEUS}"
          },
          "expr": "sum(storj_sat_month_ingress{job=~\"$job.*\"})",
          "format": "time_series",
          "hide": false,
          "legendFormat": "SumIn {{job}}",
          "refId": "D"
        }
      ],
      "title": "$job - Net IO",
      "type": "timeseries"
    },
    {
      "datasource": {
        "type": "prometheus",
        "uid": "${DS_PROMETHEUS}"
      },
      "fieldConfig": {
        "defaults": {
          "color": {
            "mode": "thresholds"
          },
          "mappings": [],
          "thresholds": {
            "mode": "absolute",
            "steps": [
              {
                "color": "red",
                "value": null
              },
              {
                "color": "#EAB839",
                "value": 97
              },
              {
                "color": "green",
                "value": 99
              }
            ]
          }
        },
        "overrides": []
      },
      "gridPos": {
        "h": 7,
        "w": 2,
        "x": 0,
        "y": 36
      },
      "hideTimeOverride": true,
      "id": 647,
      "options": {
        "colorMode": "value",
        "graphMode": "area",
        "justifyMode": "auto",
        "orientation": "auto",
        "reduceOptions": {
          "calcs": [
            "lastNotNull"
          ],
          "fields": "",
          "values": false
        },
        "textMode": "auto"
      },
      "pluginVersion": "8.5.5",
      "targets": [
        {
          "datasource": {
            "type": "prometheus",
            "uid": "${DS_PROMETHEUS}"
          },
          "editorMode": "code",
          "exemplar": false,
          "expr": "avg(storj_sat_audit{job=~\"$job.*\", type=~\"auditScore\"}*100)",
          "instant": false,
          "interval": "",
          "legendFormat": "Satellite: {{satellite}}",
          "range": true,
          "refId": "A"
        }
      ],
      "timeFrom": "30d",
      "title": "Audit (30d)",
      "type": "stat"
    },
    {
      "datasource": {
        "type": "prometheus",
        "uid": "${DS_PROMETHEUS}"
      },
      "fieldConfig": {
        "defaults": {
          "color": {
            "mode": "thresholds"
          },
          "mappings": [],
          "thresholds": {
            "mode": "absolute",
            "steps": [
              {
                "color": "red",
                "value": null
              },
              {
                "color": "#EAB839",
                "value": 97
              },
              {
                "color": "green",
                "value": 99
              }
            ]
          }
        },
        "overrides": []
      },
      "gridPos": {
        "h": 7,
        "w": 2,
        "x": 2,
        "y": 36
      },
      "hideTimeOverride": true,
      "id": 646,
      "options": {
        "colorMode": "value",
        "graphMode": "area",
        "justifyMode": "auto",
        "orientation": "auto",
        "reduceOptions": {
          "calcs": [
            "lastNotNull"
          ],
          "fields": "",
          "values": false
        },
        "textMode": "auto"
      },
      "pluginVersion": "8.5.5",
      "targets": [
        {
          "datasource": {
            "type": "prometheus",
            "uid": "${DS_PROMETHEUS}"
          },
          "editorMode": "code",
          "expr": "avg(storj_sat_audit{job=~\"$job.*\", type=~\"onlineScore\"}*100)",
          "hide": false,
          "legendFormat": "Satellite: {{satellite}}",
          "range": true,
          "refId": "B"
        }
      ],
      "timeFrom": "30d",
      "title": "Online (30d)",
      "type": "stat"
    },
    {
      "datasource": {
        "type": "prometheus",
        "uid": "${DS_PROMETHEUS}"
      },
      "fieldConfig": {
        "defaults": {
          "color": {
            "mode": "thresholds"
          },
          "mappings": [],
          "thresholds": {
            "mode": "absolute",
            "steps": [
              {
                "color": "red",
                "value": null
              },
              {
                "color": "#EAB839",
                "value": 97
              },
              {
                "color": "green",
                "value": 99
              }
            ]
          }
        },
        "overrides": []
      },
      "gridPos": {
        "h": 7,
        "w": 2,
        "x": 4,
        "y": 36
      },
      "hideTimeOverride": true,
      "id": 611,
      "options": {
        "colorMode": "value",
        "graphMode": "area",
        "justifyMode": "auto",
        "orientation": "auto",
        "reduceOptions": {
          "calcs": [
            "lastNotNull"
          ],
          "fields": "",
          "values": false
        },
        "textMode": "auto"
      },
      "pluginVersion": "8.5.5",
      "targets": [
        {
          "datasource": {
            "type": "prometheus",
            "uid": "${DS_PROMETHEUS}"
          },
          "editorMode": "code",
          "expr": "avg(storj_sat_audit{job=~\"$job.*\", type=~\"suspensionScore\"}*100)",
          "hide": false,
          "legendFormat": "Satellite: {{satellite}}",
          "range": true,
          "refId": "C"
        }
      ],
      "timeFrom": "30d",
      "title": "Suspension (30d)",
      "type": "stat"
    },
    {
      "datasource": {
        "type": "prometheus",
        "uid": "${DS_PROMETHEUS}"
      },
      "description": "",
      "fieldConfig": {
        "defaults": {
          "color": {
            "mode": "thresholds"
          },
          "decimals": 2,
          "mappings": [],
          "thresholds": {
            "mode": "absolute",
            "steps": [
              {
                "color": "red",
                "value": null
              },
              {
                "color": "green",
                "value": 0
              }
            ]
          },
          "unit": "decbytes"
        },
        "overrides": []
      },
      "gridPos": {
        "h": 7,
        "w": 3,
        "x": 6,
        "y": 36
      },
      "hideTimeOverride": true,
      "id": 762,
      "options": {
        "colorMode": "value",
        "graphMode": "area",
        "justifyMode": "auto",
        "orientation": "auto",
        "reduceOptions": {
          "calcs": [
            "diff"
          ],
          "fields": "",
          "values": false
        },
        "textMode": "auto"
      },
      "pluginVersion": "8.5.5",
      "targets": [
        {
          "datasource": {
            "type": "prometheus",
            "uid": "${DS_PROMETHEUS}"
          },
          "expr": "sum(storj_total_diskspace{type=\"used\", job=~\"$job.*\"})",
          "hide": false,
          "refId": "A"
        }
      ],
      "timeFrom": "24h",
      "title": "Change in Data (24h)",
      "type": "stat"
    },
    {
      "datasource": {
        "type": "prometheus",
        "uid": "${DS_PROMETHEUS}"
      },
      "description": "",
      "fieldConfig": {
        "defaults": {
          "color": {
            "mode": "thresholds"
          },
          "decimals": 2,
          "mappings": [],
          "thresholds": {
            "mode": "absolute",
            "steps": [
              {
                "color": "red",
                "value": null
              },
              {
                "color": "green",
                "value": 0
              }
            ]
          },
          "unit": "decbytes"
        },
        "overrides": []
      },
      "gridPos": {
        "h": 7,
        "w": 3,
        "x": 9,
        "y": 36
      },
      "hideTimeOverride": true,
      "id": 799,
      "options": {
        "colorMode": "value",
        "graphMode": "area",
        "justifyMode": "auto",
        "orientation": "auto",
        "reduceOptions": {
          "calcs": [
            "diff"
          ],
          "fields": "",
          "values": false
        },
        "textMode": "auto"
      },
      "pluginVersion": "8.5.5",
      "targets": [
        {
          "datasource": {
            "type": "prometheus",
            "uid": "${DS_PROMETHEUS}"
          },
          "expr": "sum(storj_total_diskspace{type=\"used\", job=~\"$job.*\"})",
          "hide": false,
          "refId": "C"
        }
      ],
      "timeFrom": "30d",
      "title": "Change in Data (30d)",
      "type": "stat"
    },
    {
      "datasource": {
        "type": "prometheus",
        "uid": "${DS_PROMETHEUS}"
      },
      "fieldConfig": {
        "defaults": {
          "color": {
            "mode": "palette-classic"
          },
          "custom": {
            "axisLabel": "",
            "axisPlacement": "auto",
            "barAlignment": 0,
            "drawStyle": "line",
            "fillOpacity": 0,
            "gradientMode": "none",
            "hideFrom": {
              "legend": false,
              "tooltip": false,
              "viz": false
            },
            "lineInterpolation": "linear",
            "lineWidth": 1,
            "pointSize": 5,
            "scaleDistribution": {
              "type": "linear"
            },
            "showPoints": "auto",
            "spanNulls": false,
            "stacking": {
              "group": "A",
              "mode": "none"
            },
            "thresholdsStyle": {
              "mode": "off"
            }
          },
          "decimals": 2,
          "mappings": [],
          "thresholds": {
            "mode": "absolute",
            "steps": [
              {
                "color": "green",
                "value": null
              },
              {
                "color": "red",
                "value": 80
              }
            ]
          },
          "unit": "currencyUSD"
        },
        "overrides": []
      },
      "gridPos": {
        "h": 7,
        "w": 9,
        "x": 12,
        "y": 36
      },
      "hideTimeOverride": true,
      "id": 699,
      "options": {
        "legend": {
          "calcs": [],
          "displayMode": "hidden",
          "placement": "bottom"
        },
        "tooltip": {
          "mode": "single",
          "sort": "none"
        }
      },
      "targets": [
        {
          "datasource": {
            "type": "prometheus",
            "uid": "${DS_PROMETHEUS}"
          },
          "editorMode": "code",
          "expr": "sum(storj_payout_currentMonth{type=~\"currentMonthExpectations\",job=~\"$job.*\"}) by (job) / 100",
          "legendFormat": "Change",
          "range": true,
          "refId": "A"
        },
        {
          "datasource": {
            "type": "prometheus",
            "uid": "${DS_PROMETHEUS}"
          },
          "editorMode": "code",
          "expr": "avg_over_time(storj_payout_currentMonth{type=~\"currentMonthExpectations\",job=~\"$job.*\"}[24h:5m]) / 100",
          "hide": false,
          "legendFormat": "Moving Average",
          "range": true,
          "refId": "B"
        }
      ],
      "timeFrom": "6M",
      "title": "Payout Expectations (Last 6 Months)",
      "type": "timeseries"
    },
    {
      "datasource": {
        "type": "prometheus",
        "uid": "${DS_PROMETHEUS}"
      },
      "description": "",
      "fieldConfig": {
        "defaults": {
          "color": {
            "mode": "thresholds"
          },
          "decimals": 2,
          "mappings": [],
          "thresholds": {
            "mode": "absolute",
            "steps": [
              {
                "color": "red",
                "value": null
              },
              {
                "color": "green",
                "value": 0
              }
            ]
          },
          "unit": "currencyUSD"
        },
        "overrides": []
      },
      "gridPos": {
        "h": 7,
        "w": 3,
        "x": 21,
        "y": 36
      },
      "id": 729,
      "options": {
        "colorMode": "value",
        "graphMode": "area",
        "justifyMode": "auto",
        "orientation": "auto",
        "reduceOptions": {
          "calcs": [
            "diff"
          ],
          "fields": "",
          "values": false
        },
        "textMode": "auto"
      },
      "pluginVersion": "8.5.5",
      "targets": [
        {
          "datasource": {
            "type": "prometheus",
            "uid": "${DS_PROMETHEUS}"
          },
          "editorMode": "code",
          "expr": "sum(delta(storj_payout_currentMonth{type=~\"currentMonthExpectations\",job=~\"$job.*\"}[24h])/100)",
          "legendFormat": "{{job}}",
          "range": true,
          "refId": "A"
        }
      ],
      "title": "Change in Payout (last 24 hours)",
      "type": "stat"
    }
  ],
  "refresh": false,
  "schemaVersion": 36,
  "style": "dark",
  "tags": [
    "storj",
    "docker",
    "prometheus",
    "exporter"
  ],
  "templating": {
    "list": [
      {
        "current": {
          "selected": false,
          "text": "Prometheus",
          "value": "Prometheus"
        },
        "hide": 0,
        "includeAll": false,
        "multi": false,
        "name": "datasource",
        "options": [],
        "query": "prometheus",
        "queryValue": "",
        "refresh": 1,
        "regex": "",
        "skipUrlSync": false,
        "type": "datasource"
      },
      {
        "current": {},
        "datasource": {
          "type": "prometheus",
          "uid": "${DS_PROMETHEUS}"
        },
        "definition": "label_values(job)",
        "hide": 0,
        "includeAll": true,
        "label": "Node",
        "multi": true,
        "name": "job",
        "options": [],
        "query": {
          "query": "label_values(job)",
          "refId": "StandardVariableQuery"
        },
        "refresh": 1,
        "regex": ".*storj.*",
        "skipUrlSync": false,
        "sort": 1,
        "type": "query"
      }
    ]
  },
  "time": {
    "from": "now-15m",
    "to": "now"
  },
  "timepicker": {
    "refresh_intervals": [
      "5s",
      "10s",
      "30s",
      "1m",
      "5m",
      "15m",
      "30m",
      "1h",
      "2h",
      "1d"
    ]
  },
  "timezone": "",
  "title": "Storj-Exporter",
  "uid": "teLFQE2Wk",
  "version": 9,
  "weekStart": ""
}
